pgvessel/__init__.py
pgvessel/main.py
pgvessel/_static_files_/__init__.py
pgvessel/_static_files_/logging.conf
pgvessel-0.2.0.dist-info/LICENSE
pgvessel-0.2.0.dist-info/METADATA
pgvessel-0.2.0.dist-info/WHEEL
pgvessel-0.2.0.dist-info/entry_points.txt
pgvessel-0.2.0.dist-info/top_level.txt
pgvessel-0.2.0.dist-info/RECORD
