Metadata-Version: 2.1
Name: pgvessel
Version: 0.2.0
Summary: Backup tool for postgres. Uses pg_recievewal and pg_basebackup. Uploads files to S3 bucket.
Home-page: https://gitlab.com/neonducks/pgvessel.git
Author: neonducks
Author-email: neonducks@yandex.com
License: MIT
Project-URL: Source, https://gitlab.com/neonducks/pgvessel.git
Project-URL: Bug Tracker, https://gitlab.com/neonducks/pgvessel/-/issues
Platform: UNKNOWN
Classifier: Programming Language :: Python :: 3
Classifier: License :: OSI Approved :: MIT License
Classifier: Operating System :: POSIX
Requires-Python: >=3.6
Requires-Dist: boto3 (==1.17.42)
